README
setup.py
alidayu/__init__.py
alidayu.egg-info/PKG-INFO
alidayu.egg-info/SOURCES.txt
alidayu.egg-info/dependency_links.txt
alidayu.egg-info/top_level.txt
alidayu.egg-info/zip-safe
alidayu/api/__init__.py
alidayu/api/base.py
alidayu/api/rest/AlibabaAliqinFcFlowChargeProvinceRequest.py
alidayu/api/rest/AlibabaAliqinFcFlowChargeRequest.py
alidayu/api/rest/AlibabaAliqinFcFlowGradeRequest.py
alidayu/api/rest/AlibabaAliqinFcFlowQueryRequest.py
alidayu/api/rest/AlibabaAliqinFcSmsNumQueryRequest.py
alidayu/api/rest/AlibabaAliqinFcSmsNumSendRequest.py
alidayu/api/rest/AlibabaAliqinFcTtsNumSinglecallRequest.py
alidayu/api/rest/AlibabaAliqinFcVoiceNumDoublecallRequest.py
alidayu/api/rest/AlibabaAliqinFcVoiceNumSinglecallRequest.py
alidayu/api/rest/AppipGetRequest.py
alidayu/api/rest/AreasGetRequest.py
alidayu/api/rest/HttpdnsGetRequest.py
alidayu/api/rest/KfcKeywordSearchRequest.py
alidayu/api/rest/TimeGetRequest.py
alidayu/api/rest/TopAuthTokenCreateRequest.py
alidayu/api/rest/TopAuthTokenRefreshRequest.py
alidayu/api/rest/TopIpoutGetRequest.py
alidayu/api/rest/TopSecretGetRequest.py
alidayu/api/rest/TopatsResultGetRequest.py
alidayu/api/rest/TopatsTaskDeleteRequest.py
alidayu/api/rest/__init__.py