Metadata-Version: 1.1
Name: alidayu
Version: 1.0.2
Summary: 阿里大于的python接口库，兼容python2和python3.
Home-page: https://github.com/0x5010/alidayu
Author: 0x5010
Author-email: 0xh4cker@email.com
License: UNKNOWN
Keywords: alidayu python package
Platform: UNKNOWN
Classifier: License :: OSI Approved :: MIT License
Classifier: Programming Language :: Python
Classifier: Intended Audience :: Developers
Classifier: Operating System :: OS Independent
